src_search/app.py
src_search/data.pkl.gz
src_search-0.1.1.dist-info/METADATA
src_search-0.1.1.dist-info/WHEEL
src_search-0.1.1.dist-info/entry_points.txt
src_search-0.1.1.dist-info/RECORD
