Metadata-Version: 2.3
Name: src-search
Version: 0.1.1
Summary: A tkinter GUI application for searching through source code and documentation
Author: Your Name
Author-email: your.email@example.com
Requires-Python: >=3.8
Classifier: Programming Language :: Python :: 3
Classifier: Programming Language :: Python :: 3.8
Classifier: Programming Language :: Python :: 3.9
Classifier: Programming Language :: Python :: 3.10
Classifier: Programming Language :: Python :: 3.11
Classifier: Programming Language :: Python :: 3.12
Classifier: Programming Language :: Python :: 3.13
